meijian/__init__.py
meijian/convert.py
meijian/translate.py
meijian-1.0.1.dist-info/LICENSE
meijian-1.0.1.dist-info/METADATA
meijian-1.0.1.dist-info/WHEEL
meijian-1.0.1.dist-info/top_level.txt
meijian-1.0.1.dist-info/RECORD
