Metadata-Version: 2.1
Name: meijian
Version: 1.0.1
Summary: meijian utils
Home-page: https://github.com/pypa/sampleproject
Author: p
Author-email: author@example.com
License: UNKNOWN
Platform: UNKNOWN
Classifier: Programming Language :: Python :: 3
Classifier: License :: OSI Approved :: MIT License
Classifier: Operating System :: OS Independent
Requires-Python: >=3.5
License-File: LICENSE
